CHANGES.txt
LICENSE.txt
MANIFEST.in
README.rst
setup.py
version.txt
agilegeo/__init__.py
agilegeo.egg-info/PKG-INFO
agilegeo.egg-info/SOURCES.txt
agilegeo.egg-info/dependency_links.txt
agilegeo.egg-info/top_level.txt
agilegeo/attribute/__init__.py
agilegeo/attribute/dipsteer.py
agilegeo/attribute/energy.py
agilegeo/attribute/similarity.py
agilegeo/attribute/spectraldecomp.py
agilegeo/attribute/spectrogram.py
agilegeo/avo/__init__.py
agilegeo/avo/fluidsub.py
agilegeo/avo/moduli.py
agilegeo/avo/reflection.py
agilegeo/avo/timedepthconv.py
agilegeo/util/__init__.py
agilegeo/util/utility.py
agilegeo/wavelet/__init__.py
agilegeo/wavelet/wavelets.py
docs/_build/html/_sources/agilegeo.attribute.txt
docs/_build/html/_sources/agilegeo.avo.txt
docs/_build/html/_sources/agilegeo.txt
docs/_build/html/_sources/agilegeo.util.txt
docs/_build/html/_sources/agilegeo.wavelet.txt
docs/_build/html/_sources/index.txt
docs/_build/html/_sources/modules.txt