Metadata-Version: 1.0
Name: agilegeo
Version: 0.1.6
Summary: Useful geophysics functions
Home-page: http://pypi.python.org/pypi/agilegeo/
Author: Agile Geoscience
Author-email: hello@agilegeoscience.com
License: LICENSE.txt
Platform: UNKNOWN
